{
  "FILENAME": "filesystem-1.0.0-13-any.pkg.tar.zst",
  "NAME": "filesystem",
  "BASE": "filesystem",
  "VERSION": "1.0.0-13",
  "DESC": "The base directory structure and a few core files for the system.",
  "GROUPS": [
    "base"
  ],
  "CSIZE": "244063",
  "ISIZE": "827442",
  "MD5SUM": "a73ceb5d2d0a4908c2a7bf6c65d85d34",
  "SHA256SUM": "14e7dad0337e18d2dc77c0d71e9538bb1ae97ce8dd64dbbf76f9449c9ebe190c",
  "PGPSIG": "iF4EABYCAAYFAmdfoxIACgkQw1jnDXfq/1Q2+gD/WbK7o2eUnzyqTXhua61Fb6wj2kJP71qIthrsL04DQtEBAISainlM9hlpVPHeaS32BLWfi4xUvgfO7cAm7OmyM8IB",
  "URL": "https://os.ewe.moe",
  "LICENSE": [
    "MIT"
  ],
  "ARCH": "any",
  "BUILDDATE": "1734321165",
  "PACKAGER": "eweos-loong64-3a6000worker1 <eweos-loong64-3a6000worker1@workers.os-build.ewe.moe>",
  "REPO": "main"
}
