{
  "FILENAME": "glib-networking-2.80.1-1-x86_64.pkg.tar.zst",
  "NAME": "glib-networking",
  "BASE": "glib-networking",
  "VERSION": "2.80.1-1",
  "DESC": "Network extensions for GLib",
  "CSIZE": "167898",
  "ISIZE": "632338",
  "MD5SUM": "10912c060bad551530e38ba177b2e431",
  "SHA256SUM": "db1a88bf076298465e877b026c959bde5834287fcaac163712852b73bce1a808",
  "PGPSIG": "iF4EABYCAAYFAmeEG4wACgkQw1jnDXfq/1TYZQEAlEE3/OdSfRPI4SSg1toJsZWTEbxs9L7m08PFLe4/n+QA/3+NZqS9IhqS4liiaI43Z+dLawCyoNXCuMEUoZ73ZlcF",
  "URL": "https://gitlab.gnome.org/GNOME/glib-networking",
  "LICENSE": [
    "LGPL-2.1-or-later"
  ],
  "ARCH": "x86_64",
  "BUILDDATE": "1736711404",
  "PACKAGER": "eweos-x8664-worker1 <eweos-x8664-worker1@workers.os-build.ewe.moe>",
  "DEPENDS": [
    "glib2",
    "gsettings-system-schemas",
    "libproxy"
  ],
  "MAKEDEPENDS": [
    "git",
    "gsettings-desktop-schemas",
    "meson"
  ],
  "CHECKDEPENDS": [
    "ca-certificates"
  ],
  "REPO": "main"
}
