{
  "FILENAME": "graphene-1.10.8-2-x86_64.pkg.tar.zst",
  "NAME": "graphene",
  "BASE": "graphene",
  "VERSION": "1.10.8-2",
  "DESC": "A thin layer of graphic data types",
  "CSIZE": "135230",
  "ISIZE": "1003342",
  "MD5SUM": "a34449f9a3370428f1c57d3f7b06ab18",
  "SHA256SUM": "23ef6f8a74442612d36c0803b0ae39775c2b2855ef1f45dd912137af16909878",
  "PGPSIG": "iF4EABYCAAYFAmcSGyQACgkQw1jnDXfq/1TyagEA8QWABJhHSAYLML6t5auVypSDuVMdcOqmKqICF6Lv4iwA/0KMhro/oy4pb8vB5LtpFybv37duSN9EModrR7fm/8IE",
  "URL": "https://ebassi.github.io/graphene/",
  "LICENSE": [
    "MIT"
  ],
  "ARCH": "x86_64",
  "BUILDDATE": "1729239840",
  "PACKAGER": "yukari-dpc <yukari-dpc@workers.os-build.ewe.moe>",
  "DEPENDS": [
    "glib"
  ],
  "MAKEDEPENDS": [
    "gobject-introspection",
    "meson",
    "glib"
  ],
  "REPO": "main"
}
