{
  "FILENAME": "gst-rtsp-server-1.26.6-1-loongarch64.pkg.tar.zst",
  "NAME": "gst-rtsp-server",
  "BASE": "gstreamer",
  "VERSION": "1.26.6-1",
  "DESC": "GStreamer multimedia framework - rtsp server",
  "CSIZE": "171946",
  "ISIZE": "458224",
  "MD5SUM": "32c6f444d3b9bb65109a5e8d69068c73",
  "SHA256SUM": "1bb838fc91e7b0bfc1edcd63109b3aeec48783428f296afb7bf94ea452078111",
  "PGPSIG": "iHUEABYCAB0WIQRMXo0KXwPHuyFNJ/jDWOcNd+r/VAUCaMowqwAKCRDDWOcNd+r/VBftAP9pk5tSr0IZDFSzS2SVvLuXR8VQH6JakGk/GxryB01ZcQD+KpFvr+gTw264BWj8Lv+K0kT6lDww1J5IoR5B6VyuSAY=",
  "URL": "https://gstreamer.freedesktop.org/",
  "LICENSE": [
    "LGPL-2.1-or-later"
  ],
  "ARCH": "loongarch64",
  "BUILDDATE": "1758080380",
  "PACKAGER": "eweos-loong64-3a6000worker1 <abuild@eweos-loong64-3a6000worker1>",
  "DEPENDS": [
    "musl",
    "gstreamer=1.26.6-1",
    "gst-plugins-base-libs=1.26.6-1",
    "zlib"
  ],
  "MAKEDEPENDS": [
    "meson",
    "samurai",
    "glib2",
    "gobject-introspection",
    "libdrm",
    "python-gobject",
    "bash-completion",
    "rust",
    "alsa-lib",
    "libopus",
    "libogg",
    "pango",
    "libvorbis",
    "iso-codes",
    "libglvnd",
    "mesa",
    "wayland-protocols",
    "nasm",
    "cairo",
    "libflac",
    "gdk-pixbuf",
    "gtk3",
    "libjpeg",
    "libpng",
    "libpulse",
    "qt6-base",
    "qt6-wayland",
    "qt6-tools",
    "qt6-shadertools",
    "libvpx",
    "lame",
    "vulkan-headers",
    "libdrm",
    "shaderc",
    "linux-headers",
    "libva",
    "libsoup3",
    "libaom",
    "libbz2",
    "curl",
    "fluidsynth",
    "gsm",
    "libopus",
    "libsndfile",
    "libxml2",
    "libsrt",
    "libwebp",
    "x265",
    "openal-soft",
    "openexr",
    "libjpeg",
    "librsvg",
    "vulkan-icd-loader",
    "libass",
    "lcms2",
    "openjpeg2",
    "json-glib",
    "ffmpeg",
    "svt-av1",
    "mpg123",
    "taglib",
    "zxing-cpp"
  ],
  "REPO": "main"
}
