{
  "FILENAME": "harfbuzz-cairo-10.4.0-1-x86_64.pkg.tar.zst",
  "NAME": "harfbuzz-cairo",
  "BASE": "harfbuzz",
  "VERSION": "10.4.0-1",
  "DESC": "OpenType text shaping engine - Cairo integration",
  "CSIZE": "19663",
  "ISIZE": "37898",
  "MD5SUM": "23b0f0300bd9ffc19fd21a2ef371e3d6",
  "SHA256SUM": "7491c6290c9f3b1cdca7bb039f7e63f21ec7511d67cb00ba9c3bd1a187bdd657",
  "PGPSIG": "iF4EABYCAAYFAmfJV4cACgkQw1jnDXfq/1Tn5QD+ON9/3njgkfLTz/9hmBpRJNYWZdWXCiCYCRS/LtRPaKsBAKTdvS44eL3PE6q8e9p1iuRwuebXEg0p0hcEMLPEnkMG",
  "URL": "https://www.freedesktop.org/wiki/Software/HarfBuzz",
  "LICENSE": [
    "MIT"
  ],
  "ARCH": "x86_64",
  "BUILDDATE": "1741248787",
  "PACKAGER": "eweos-x8664-worker1 <eweos-x8664-worker1@workers.os-build.ewe.moe>",
  "DEPENDS": [
    "cairo",
    "freetype2",
    "glib2",
    "graphite",
    "harfbuzz",
    "libcairo.so",
    "libharfbuzz.so"
  ],
  "PROVIDES": [
    "libharfbuzz-cairo.so"
  ],
  "REPO": "main"
}
