{ "Repository": "main", "Name": "jbigkit", "Version": "2.1-1", "Description": "Data compression library/utilities for bi-level high-resolution images", "Architecture": "riscv64", "URL": "https://www.cl.cam.ac.uk/~mgk25/jbigkit/", "Licenses": "GPL-2.0-or-later", "Groups": "None", "Provides": "None", "Depends On": "None", "Optional Deps": "None", "Required By": "None", "Optional For": "imagemagick", "Conflicts With": "None", "Replaces": "None", "Download Size": "51.94 KiB", "Installed Size": "114.27 KiB", "Packager": "visionfive2-1 <visionfive2-1@workers.os-build.ewe.moe>", "Build Date": "Mon Dec 23 05:35:44 2024", "MD5 Sum": "7ec13bb6641c674312ca0bb1fa1f8fc1", "SHA-256 Sum": "d2ad85d9b658eed274061d138c7c0bdb1585b84fbc52e3b8c4e4e2cf7372abf3", "Signatures": "C358E70D77EAFF54", "Extended Data": "None" }
