{ "Repository": "main", "Name": "kirc", "Version": "0.3.2-1", "Description": "A tiny IRC client written in POSIX C99", "Architecture": "aarch64", "URL": "https://github.com/mcpcpc/kirc", "Licenses": "MIT", "Groups": "None", "Provides": "None", "Depends On": "musl", "Optional Deps": "None", "Required By": "None", "Optional For": "None", "Conflicts With": "None", "Replaces": "None", "Download Size": "13.14 KiB", "Installed Size": "21.62 KiB", "Packager": "Unknown Packager", "Build Date": "Fri Apr 19 17:22:57 2024", "MD5 Sum": "7c2b0479a396a479ff0c39a0cfca4188", "SHA-256 Sum": "c6e994c462cf695b963f6b61af4d125976a748e6891601d9ed128e86145bb716", "Signatures": "C358E70D77EAFF54", "Extended Data": "None" }
