{ "Repository": "main", "Name": "kpackage", "Version": "6.6.0-2", "Description": "Framework that lets applications manage user installable packages of non-binary assets", "Architecture": "loongarch64", "URL": "https://community.kde.org/Frameworks", "Licenses": "LGPL-2.0-only LGPL-3.0-only", "Groups": "kf6", "Provides": "None", "Depends On": "karchive kcoreaddons ki18n qt6-base", "Optional Deps": "None", "Required By": "knewstuff", "Optional For": "None", "Conflicts With": "None", "Replaces": "None", "Download Size": "162.64 KiB", "Installed Size": "590.81 KiB", "Packager": "eweos-loong64-3a6000worker1 <eweos-loong64-3a6000worker1@workers.os-build.ewe.moe>", "Build Date": "Mon Oct 21 03:06:19 2024", "MD5 Sum": "318eaba4be9420857edec38451fe43ba", "SHA-256 Sum": "21f0ab34b5502f910faf29fce7aedef35f8228602b47da6abfe3190e17c4ae85", "Signatures": "C358E70D77EAFF54", "Extended Data": "None" }
