{
  "FILENAME": "kwidgetsaddons-6.15.0-2-loongarch64.pkg.tar.zst",
  "NAME": "kwidgetsaddons",
  "BASE": "kwidgetsaddons",
  "VERSION": "6.15.0-2",
  "DESC": "Addons to QtWidgets",
  "GROUPS": "kf6",
  "CSIZE": "1833238",
  "ISIZE": "5260995",
  "MD5SUM": "e88bdb316cadcaa35d3409961a2b91af",
  "SHA256SUM": "0e169a24b4fb1e7aa863654ad788a49f50519d7265819424b6d6d37c99c7e9bc",
  "PGPSIG": "iF0EABYCAAYFAmhb2PcACgkQw1jnDXfq/1SlFQD0D8AJmcqK7/9XHSMw6sSLve1Sf6hgomjhZcRxLBymHQD/a9n+Ff0XZr4aBqShRF9V/o/U2F4/4BSQaUfhK+LjjgE=",
  "URL": "https://community.kde.org/Frameworks",
  "LICENSE": [
    "LGPL-2.0-only",
    "LGPL-3.0-only"
  ],
  "ARCH": "loongarch64",
  "BUILDDATE": "1750849929",
  "PACKAGER": "eweos-loong64-3a6000worker1 <eweos-loong64-3a6000worker1@workers.os-build.ewe.moe>",
  "DEPENDS": [
    "qt6-base"
  ],
  "MAKEDEPENDS": [
    "extra-cmake-modules",
    "qt6-tools"
  ],
  "REPO": "main"
}
