{
  "FILENAME": "libavif-1.3.0-1-riscv64.pkg.tar.zst",
  "NAME": "libavif",
  "BASE": "libavif",
  "VERSION": "1.3.0-1",
  "DESC": "Library for encoding and decoding .avif files",
  "CSIZE": "257450",
  "ISIZE": "624270",
  "MD5SUM": "64ae628e8bd9e203dfc522a02eba648b",
  "SHA256SUM": "9b38aafc7ff934c2ea48438ebcf2b934b4b9297b908dc8e47d0a964c2ebdd4f6",
  "PGPSIG": "iF4EABYCAAYFAmgybDUACgkQw1jnDXfq/1QxqAEA+SztvH3OHeWGxfjYTy9ME+Tt+iOjA1iEO8/jRfhpiqgBAO+chkTuWX9FepFB9hYEWBZr6r8wn48tkLK7werHk20O",
  "URL": "https://github.com/AOMediaCodec/libavif",
  "LICENSE": [
    "LicenseRef-libavif"
  ],
  "ARCH": "riscv64",
  "BUILDDATE": "1748135239",
  "PACKAGER": "visionfive2-1 <visionfive2-1@workers.os-build.ewe.moe>",
  "DEPENDS": [
    "aom",
    "dav1d",
    "librav1e.so",
    "svt-av1",
    "libpng",
    "libjpeg-turbo",
    "libyuv",
    "libwebp"
  ],
  "MAKEDEPENDS": [
    "cmake",
    "gdk-pixbuf2",
    "git",
    "nasm"
  ],
  "REPO": "main"
}
