{ "Repository": "main", "Name": "libelf", "Version": "0.192-1", "Description": "libelf is a free ELF object file access library (libraries)", "Architecture": "loongarch64", "URL": "https://sourceware.org/elfutils/", "Licenses": "LGPL3 GPL3", "Groups": "None", "Provides": "libasm libdebuginfod libdw libelf", "Depends On": "xz zlib musl-fts musl-obstack libuargp", "Optional Deps": "None", "Required By": "elfutils libbpf libva-mesa-driver mesa openmp", "Optional For": "None", "Conflicts With": "None", "Replaces": "None", "Download Size": "591.14 KiB", "Installed Size": "3343.34 KiB", "Packager": "eweos-loong64-3a6000worker1 <eweos-loong64-3a6000worker1@workers.os-build.ewe.moe>", "Build Date": "Wed Oct 23 10:35:30 2024", "MD5 Sum": "030885514422b92a51674124c6c8545b", "SHA-256 Sum": "4a2c25fe2ead1de2ceb0473be1327a0db84e511c3e5c7cf22b635fedee519126", "Signatures": "C358E70D77EAFF54", "Extended Data": "None" }
