{
  "FILENAME": "libnewt-0.52.24-3-aarch64.pkg.tar.zst",
  "NAME": "libnewt",
  "BASE": "libnewt",
  "VERSION": "0.52.24-3",
  "DESC": "Not Erik's Windowing Toolkit - text mode windowing with slang",
  "CSIZE": "101775",
  "ISIZE": "259161",
  "MD5SUM": "748d9b7201a697c20950dcd621104112",
  "SHA256SUM": "05d1be8535735b1f31f822cd9c80900cadc773d4b0c34a624927d4b5b5b71219",
  "PGPSIG": "iF4EABYCAAYFAmdP2CEACgkQw1jnDXfq/1SaUQD+O4h+iAWdOswfVKikvrIhV2KLwFc1/LPblRvNM93yUWkBAMaEl5plt38Aw06Bp7BlPvnKSRCpt0jjV0YeDvY0+WMD",
  "URL": "https://pagure.io/newt",
  "LICENSE": [
    "GPL"
  ],
  "ARCH": "aarch64",
  "BUILDDATE": "1733286092",
  "PACKAGER": "venus <venus@workers.os-build.ewe.moe>",
  "DEPENDS": [
    "popt",
    "slang"
  ],
  "OPTDEPENDS": [
    "python: libnewt support with the _snack module",
    "tcl: whiptcl support"
  ],
  "REPO": "main"
}
