{
  "FILENAME": "libnfnetlink-1.0.2-3-loongarch64.pkg.tar.zst",
  "NAME": "libnfnetlink",
  "BASE": "libnfnetlink",
  "VERSION": "1.0.2-3",
  "DESC": "Low-level library for netfilter related kernel/userspace communication",
  "CSIZE": "16798",
  "ISIZE": "33828",
  "MD5SUM": "16ad9615c3dcd417f4941ef1ba6899d6",
  "SHA256SUM": "49d30e2b3c276c124d5b8384d615c5f322c22f76d184cbf51f0fee83fcbcb3b4",
  "PGPSIG": "iF4EABYCAAYFAmdX0+gACgkQw1jnDXfq/1TPuwEAszcu7Xp9hWzw3TQOu21TikHTlpjNoFwJDJKV1ODVnTEA/iaByiHdO0PaXCbCH1How+2n8iIJ9sBADdyGJfl79QgN",
  "URL": "https://www.netfilter.org/projects/libnfnetlink/",
  "LICENSE": [
    "GPL"
  ],
  "ARCH": "loongarch64",
  "BUILDDATE": "1733809343",
  "PACKAGER": "eweos-loong64-3a6000worker1 <eweos-loong64-3a6000worker1@workers.os-build.ewe.moe>",
  "DEPENDS": [
    "musl"
  ],
  "MAKEDEPENDS": [
    "linux-headers",
    "autoconf"
  ],
  "REPO": "main"
}
