{
  "FILENAME": "libnm-1.52.0-2-riscv64.pkg.tar.zst",
  "NAME": "libnm",
  "BASE": "networkmanager",
  "VERSION": "1.52.0-2",
  "DESC": "NetworkManager client library",
  "CSIZE": "1126925",
  "ISIZE": "6288559",
  "MD5SUM": "bdb864dd3d5cc99385db25f23f0f5f98",
  "SHA256SUM": "4d64bb5437581637b7b7f7e82e699212d76faff8251decb67821d1bf6323186a",
  "PGPSIG": "iF4EABYCAAYFAmgfbA0ACgkQw1jnDXfq/1TSPAEAoRvV3ZMiah2rfsfyOYJW+8JGOCJ3Qb18mCiYYJa211kA/3ihaWBmB0dhTBUEUYgBbj+LxqF6TxPWRnLzlFOs3E4B",
  "URL": "https://networkmanager.dev/",
  "LICENSE": [
    "LGPL-2.1-or-later"
  ],
  "ARCH": "riscv64",
  "BUILDDATE": "1746887582",
  "PACKAGER": "visionfive2-2 <visionfive2-2@workers.os-build.ewe.moe>",
  "DEPENDS": [
    "glib2",
    "nspr",
    "nss",
    "util-linux-libs"
  ],
  "PROVIDES": [
    "libnm.so"
  ],
  "MAKEDEPENDS": [
    "bash",
    "curl",
    "git",
    "glib2",
    "gobject-introspection",
    "gtk-doc",
    "jansson",
    "libndp",
    "libnewt",
    "libpsl",
    "libudev",
    "linux-headers",
    "meson",
    "nftables",
    "nspr",
    "nss",
    "python-gobject",
    "readline",
    "vala",
    "wpa_supplicant"
  ],
  "CHECKDEPENDS": [
    "python-dbus"
  ],
  "REPO": "main"
}
