{ "Repository": "main", "Name": "libslirp", "Version": "4.8.0-2", "Description": "A general purpose TCP-IP emulator.", "Architecture": "loongarch64", "URL": "https://gitlab.freedesktop.org/slirp/libslirp", "Licenses": "BSD-3-Clause", "Groups": "None", "Provides": "libslirp.so", "Depends On": "glib", "Optional Deps": "None", "Required By": "None", "Optional For": "None", "Conflicts With": "None", "Replaces": "None", "Download Size": "67.57 KiB", "Installed Size": "142.65 KiB", "Packager": "eweos-loong64-3a6000worker1 <eweos-loong64-3a6000worker1@workers.os-build.ewe.moe>", "Build Date": "Mon Dec 9 07:28:13 2024", "MD5 Sum": "77d2bd349757addfe73f187e02223768", "SHA-256 Sum": "0353d2afc185f93c18c9bfb9035cc4c1855360b82871a97fd72f5aa572578fed", "Signatures": "C358E70D77EAFF54", "Extended Data": "None" }
