{
  "FILENAME": "libseccomp-2.5.5-6-aarch64.pkg.tar.zst",
  "NAME": "libseccomp",
  "BASE": "libseccomp",
  "VERSION": "2.5.5-6",
  "DESC": "Enhanced seccomp library",
  "CSIZE": "99983",
  "ISIZE": "225524",
  "MD5SUM": "a601ee16f82f6e9c771c03a64fdc9ae6",
  "SHA256SUM": "727f3a707434349dee0830f50b254e7353da8071062f47350bfe8e20fc535f1f",
  "PGPSIG": "iF4EABYCAAYFAmdwdrwACgkQw1jnDXfq/1Sc/AD8Dbtv8WfY5X87jEdCGYMl9XIh486/WHLZY+o9oJdSuDAA/RUur2IElFNjGHN3k9NpjuJ6dR4L/63QT9iLwJ7s9R0D",
  "URL": "https://github.com/seccomp/libseccomp",
  "LICENSE": [
    "LGPL-2.1-or-later"
  ],
  "ARCH": "aarch64",
  "BUILDDATE": "1735423640",
  "PACKAGER": "venus <venus@workers.os-build.ewe.moe>",
  "DEPENDS": [
    "linux-headers"
  ],
  "PROVIDES": [
    "libseccomp.so"
  ],
  "REPO": "main"
}
