{
  "FILENAME": "libxslt-1.1.42-3-x86_64.pkg.tar.zst",
  "NAME": "libxslt",
  "BASE": "libxslt",
  "VERSION": "1.1.42-3",
  "DESC": "XML stylesheet transformation library",
  "CSIZE": "239835",
  "ISIZE": "772729",
  "MD5SUM": "5dd210d049900c4e69efd781d803d5b0",
  "SHA256SUM": "b171014cc9d22d4fcc3fcaea0b3b032b28f680f4bcb33700e9329ddc3ad7bae7",
  "PGPSIG": "iF4EABYCAAYFAmdP2SwACgkQw1jnDXfq/1TdzgD+MBI1mJFW5pSIARbzt9tgtzkQDjbDTn3ocyt/8TiLNsMBALDxRJovPeXgCYS+PhzfMQl9dkNB9kXUjZMAVY+v768O",
  "URL": "https://gitlab.gnome.org/GNOME/libxslt/-/wikis/home",
  "LICENSE": [
    "custom:MIT"
  ],
  "ARCH": "x86_64",
  "BUILDDATE": "1733286345",
  "PACKAGER": "eweos-x8664-worker1 <eweos-x8664-worker1@workers.os-build.ewe.moe>",
  "DEPENDS": [
    "libgcrypt",
    "libxml2",
    "xz"
  ],
  "PROVIDES": [
    "libxslt.so",
    "libexslt.so"
  ],
  "OPTDEPENDS": [
    "python: Python bindings"
  ],
  "REPO": "main"
}
