{
  "FILENAME": "linux-uapi-headers-6.19.6-1-aarch64.pkg.tar.zst",
  "NAME": "linux-uapi-headers",
  "BASE": "linux-uapi-headers",
  "VERSION": "6.19.6-1",
  "DESC": "Kernel headers sanitized for use in userspace",
  "CSIZE": "1935004",
  "ISIZE": "7089840",
  "MD5SUM": "596ae9c719892e63ffbc76b342d8c7ff",
  "SHA256SUM": "abf24de393e0708ab083ea972bd1de54d637041dabf9030ecc44a67fd36af5fa",
  "PGPSIG": "iHUEABYCAB0WIQRMXo0KXwPHuyFNJ/jDWOcNd+r/VAUCaanBcgAKCRDDWOcNd+r/VCUJAP0Rr6kw7e6cgBbTQShFjFZX1LHsZvtAl9Ph9iTi9pSq0gEAvqjORJPmRCw55bQS5uXXjZtAWaq3eUbGa6AIwq7lHgk=",
  "URL": "http://www.kernel.org",
  "LICENSE": [
    "GPL-2.0-only WITH Linux-syscall-note"
  ],
  "ARCH": "aarch64",
  "BUILDDATE": "1772732936",
  "PACKAGER": "venus <abuild@venus>",
  "REPLACES": [
    "linux-headers"
  ],
  "CONFLICTS": [
    "linux-headers"
  ],
  "PROVIDES": [
    "linux-headers"
  ],
  "MAKEDEPENDS": [
    "rsync"
  ],
  "REPO": "main"
}
