{ "Repository": "main", "Name": "mtr-gtk", "Version": "0.95-4", "Description": "Combines the functionality of traceroute and ping into one tool", "Architecture": "riscv64", "URL": "https://www.bitwizard.nl/mtr/", "Licenses": "GPL2", "Groups": "None", "Provides": "mtr", "Depends On": "ncurses libcap gtk3", "Optional Deps": "None", "Required By": "None", "Optional For": "None", "Conflicts With": "mtr", "Replaces": "None", "Download Size": "59.03 KiB", "Installed Size": "114.44 KiB", "Packager": "visionfive2-2 <visionfive2-2@workers.os-build.ewe.moe>", "Build Date": "Fri Aug 16 00:51:13 2024", "MD5 Sum": "7ac943b3db726f4cdfad295dcab2a3b7", "SHA-256 Sum": "6ed3b4e15aee50c95721635db76679d318a864208daa4661f94b1f3f19939aab", "Signatures": "C358E70D77EAFF54", "Extended Data": "None" }
