{
  "FILENAME": "ngspice-44.2-1-loongarch64.pkg.tar.zst",
  "NAME": "ngspice",
  "BASE": "ngspice",
  "VERSION": "44.2-1",
  "DESC": "Spice simulator for electric and electronic circuits",
  "CSIZE": "4730433",
  "ISIZE": "11812324",
  "MD5SUM": "809bb1ff20f38949a8bf8c90ca44bd92",
  "SHA256SUM": "5687b2c5606a2bdb7ff3234b56a7358409e904dfabe3a7faf774e99a3671f6ac",
  "PGPSIG": "iF4EABYCAAYFAmiqt50ACgkQw1jnDXfq/1TJGgD+MDnttcbLynvDcf1rcS72VagtWEfJhtJzWJCQ5sT8aXoBAMcMZ2BmEUJDTNVGId0joO6p2x7QnLsPMMi121cE0OkM",
  "URL": "https://ngspice.sourceforge.io/index.html",
  "LICENSE": [
    "BSD-3-Clause"
  ],
  "ARCH": "loongarch64",
  "BUILDDATE": "1756018563",
  "PACKAGER": "eweos-loong64-3a6000worker1 <eweos-loong64-3a6000worker1@workers.os-build.ewe.moe>",
  "DEPENDS": [
    "musl",
    "llvm-libs",
    "openmp"
  ],
  "PROVIDES": [
    "libngspice.so"
  ],
  "REPO": "main"
}
