{
  "FILENAME": "numactl-2.0.19-2-aarch64.pkg.tar.zst",
  "NAME": "numactl",
  "BASE": "numactl",
  "VERSION": "2.0.19-2",
  "DESC": "Utils for monitoring and controlling NUMA policies",
  "CSIZE": "48093",
  "ISIZE": "98366",
  "MD5SUM": "d0d4436950f8ecd1e1af7579b7841a15",
  "SHA256SUM": "13de8b30dfb60abccaaedea53b102d15ac1fb3671089ba4a6caf6fbb3b10c68d",
  "PGPSIG": "iF4EABYCAAYFAmijFh4ACgkQw1jnDXfq/1SYLgD+MV0+BvRgeSs3/V1cFrKy09I1XJUd7b5RcghaMJCP1nwA/0QTHl2h2Fwp4aatKoxFcfNBXvZJIzKdGSjJwQn3DlYI",
  "URL": "https://github.com/numactl/numactl",
  "LICENSE": [
    "GPL-2.0-only"
  ],
  "ARCH": "aarch64",
  "BUILDDATE": "1755519203",
  "PACKAGER": "venus <venus@workers.os-build.ewe.moe>",
  "DEPENDS": [
    "musl",
    "libnuma"
  ],
  "MAKEDEPENDS": [
    "linux-headers"
  ],
  "REPO": "main"
}
