{ "Repository": "main", "Name": "otf-overpass-nerd", "Version": "3.2.1-1", "Description": "Patched font Overpass from nerd fonts library", "Architecture": "any", "URL": "https://github.com/ryanoasis/nerd-fonts", "Licenses": "OFL-1.1-no-RFN LGPL-2.1-only", "Groups": "nerd-fonts", "Provides": "ttf-font-nerd", "Depends On": "None", "Optional Deps": "None", "Required By": "None", "Optional For": "None", "Conflicts With": "nerd-fonts-overpass", "Replaces": "nerd-fonts-overpass", "Download Size": "85.73 MiB", "Installed Size": "196.82 MiB", "Packager": "eweos-loong64-3a6000worker1 <eweos-loong64-3a6000worker1@workers.os-build.ewe.moe>", "Build Date": "Thu Oct 17 17:15:18 2024", "MD5 Sum": "8a2730c0d3cc2e49eb56164b520aeb10", "SHA-256 Sum": "63168dd1b50d13f00b15df5d3ade60245b5e7300253b83a764db3700a4503095", "Signatures": "C358E70D77EAFF54", "Extended Data": "None" }
