{
  "FILENAME": "otf-overpass-nerd-3.3.0-1-any.pkg.tar.zst",
  "NAME": "otf-overpass-nerd",
  "BASE": "font-nerd",
  "VERSION": "3.3.0-1",
  "DESC": "Patched font Overpass from nerd fonts library",
  "GROUPS": "nerd-fonts",
  "CSIZE": "96564631",
  "ISIZE": "225647062",
  "MD5SUM": "438a1ec4860c45488acba8ab920f8cb6",
  "SHA256SUM": "82f68e7d9e4b1df9c7f8278293fcc4c5f03b6997f309c2ce2b23e29d4bc4ffb2",
  "PGPSIG": "iF4EABYCAAYFAmc9jdAACgkQw1jnDXfq/1Rj0wD+L9N88Nd+21I28BVSlKN52Zyho3BydiAmlMIcpUW4LWwA/2r0Ty1GEUHZUbkk3Wy6QSX8C4zVa+qQHD9ol0Yh1WsH",
  "URL": "https://github.com/ryanoasis/nerd-fonts",
  "LICENSE": [
    "OFL-1.1-no-RFN",
    "LGPL-2.1-only"
  ],
  "ARCH": "any",
  "BUILDDATE": "1732087120",
  "PACKAGER": "venus <venus@workers.os-build.ewe.moe>",
  "REPLACES": [
    "nerd-fonts-overpass"
  ],
  "CONFLICTS": [
    "nerd-fonts-overpass"
  ],
  "PROVIDES": [
    "ttf-font-nerd"
  ],
  "REPO": "main"
}
