{
  "FILENAME": "perl-xml-sax-expat-0.51-5-any.pkg.tar.zst",
  "NAME": "perl-xml-sax-expat",
  "BASE": "perl-xml-sax-expat",
  "VERSION": "0.51-5",
  "DESC": "SAX2 Driver for Expat (XML::Parser)",
  "CSIZE": "8735",
  "ISIZE": "21629",
  "MD5SUM": "9f8d18f2318104a35b832fb9f9896d10",
  "SHA256SUM": "66da505c1a4605c862bee11d3709a9b90fbda89feaf05b47df9d7f79e4e0686c",
  "PGPSIG": "iF4EABYCAAYFAmi2dA0ACgkQw1jnDXfq/1RPuwD/by7caNPYUP3oyNApnSx65NNM6u9tlhbTplIkwbUhy4QA/3MsXrMskAjJMsZ6pZ/pnsOq5rE4uvsH/rGFzT9Of6wO",
  "URL": "https://search.cpan.org/dist/XML-SAX-Expat",
  "LICENSE": [
    "GPL",
    "PerlArtistic"
  ],
  "ARCH": "any",
  "BUILDDATE": "1756788513",
  "PACKAGER": "eweos-x8664-worker1 <eweos-x8664-worker1@workers.os-build.ewe.moe>",
  "DEPENDS": [
    "perl",
    "perl-xml-namespacesupport",
    "perl-xml-parser",
    "perl-xml-sax"
  ],
  "REPO": "main"
}
