{
  "FILENAME": "perl-cpan-requirements-dynamic-0.002-2-any.pkg.tar.zst",
  "NAME": "perl-cpan-requirements-dynamic",
  "BASE": "perl-cpan-requirements-dynamic",
  "VERSION": "0.002-2",
  "DESC": "Dynamic prerequisites in meta files.",
  "CSIZE": "8340",
  "ISIZE": "10216",
  "MD5SUM": "d1b624d9c6b62461c341fba4f3f7f664",
  "SHA256SUM": "b9e1d6e9839be3f7fe03f0264470841af90b9642184c828aee28dda4c1c2824a",
  "PGPSIG": "iF4EABYCAAYFAmi2bJkACgkQw1jnDXfq/1SLUgD8DVJTzLbSxZhnvm4mg0pAcsye2NwvYXvgC4AMp524mV8A/3egtp3L4trb2o/F0EUxpiflGuppXhdIYJm6jP/IgLYB",
  "URL": "https://metacpan.org/pod/CPAN::Requirements::Dynamic",
  "LICENSE": [
    "GPL",
    "PerlArtistic"
  ],
  "ARCH": "any",
  "BUILDDATE": "1756786599",
  "PACKAGER": "visionfive2-2 <visionfive2-2@workers.os-build.ewe.moe>",
  "DEPENDS": [
    "perl"
  ],
  "MAKEDEPENDS": [
    "perl-extutils-config",
    "perl-extutils-hascompiler"
  ],
  "REPO": "main"
}
