{
  "FILENAME": "python-msgpack-1.1.2-1-x86_64.pkg.tar.zst",
  "NAME": "python-msgpack",
  "BASE": "python-msgpack",
  "VERSION": "1.1.2-1",
  "DESC": "MessagePack serializer implementation for Python",
  "CSIZE": "96019",
  "ISIZE": "306406",
  "MD5SUM": "abd8829373acc23b460f8ebd8e2fc088",
  "SHA256SUM": "7b39939f278acc31ddecf2cc14fba53a297971d5d9fa0b4c912bd802a61d81a1",
  "PGPSIG": "iHUEABYCAB0WIQRMXo0KXwPHuyFNJ/jDWOcNd+r/VAUCaSUalgAKCRDDWOcNd+r/VFEJAQDcBMYPU94JmhMCY6/Ipk1Vbrd1xdWlDepg5XTcxH8suAEA3wI+iIcLjI7A0p7JlF7sLfThGQGl9UKZIe9sv+1LGAU=",
  "URL": "https://github.com/msgpack/msgpack-python",
  "LICENSE": [
    "Apache-2.0"
  ],
  "ARCH": "x86_64",
  "BUILDDATE": "1764039677",
  "PACKAGER": "eweos-x8664-worker1 <abuild@eweos-x8664-worker1>",
  "DEPENDS": [
    "musl",
    "python"
  ],
  "MAKEDEPENDS": [
    "cython",
    "python-setuptools",
    "python-build",
    "python-installer",
    "python-wheel"
  ],
  "CHECKDEPENDS": [
    "python-pytest"
  ],
  "REPO": "main"
}
