{
  "FILENAME": "python-platformdirs-4.3.6-2-any.pkg.tar.zst",
  "NAME": "python-platformdirs",
  "BASE": "python-platformdirs",
  "VERSION": "4.3.6-2",
  "DESC": "A library to determine platform-specific system directories",
  "CSIZE": "40022",
  "ISIZE": "249255",
  "MD5SUM": "95585ba8ef565b6af7c45d9372b2d0a2",
  "SHA256SUM": "f82b6c73a14e5a078932bd4e879b8adef7661629d2056d5e068054333145640d",
  "PGPSIG": "iF4EABYCAAYFAmdP2igACgkQw1jnDXfq/1TKOgD/QBGcceDBp1V5K8BgwEbDnW6zYHoy7AHoIB9o4HnaucsA/RQAdYd1L5fyF0i2ZZqcc/fHkY4zeVn6+UFLLkTEcMoK",
  "URL": "https://github.com/platformdirs/platformdirs",
  "LICENSE": [
    "MIT"
  ],
  "ARCH": "any",
  "BUILDDATE": "1733286637",
  "PACKAGER": "eweos-x8664-worker1 <eweos-x8664-worker1@workers.os-build.ewe.moe>",
  "DEPENDS": [
    "python"
  ],
  "REPO": "main"
}
