{
  "FILENAME": "python-auditwheel-6.5.0-1-any.pkg.tar.zst",
  "NAME": "python-auditwheel",
  "BASE": "python-auditwheel",
  "VERSION": "6.5.0-1",
  "DESC": "Auditing and relabeling cross-distribution Linux wheels.",
  "CSIZE": "130760",
  "ISIZE": "633543",
  "MD5SUM": "0ca869cf060ccceab9c84d340315bccb",
  "SHA256SUM": "636826cac0966a67be8d44a3b7053408b88db59c16f399f85653abd060c15a91",
  "PGPSIG": "iHUEABYCAB0WIQRMXo0KXwPHuyFNJ/jDWOcNd+r/VAUCaSPPgwAKCRDDWOcNd+r/VNPjAP4sVdyGAknYau5G5ESvfPCnZQY/eweQ803apZq30LZ/IQD/e2e0rgCwaskV12bI3HGzZe1/aqP/yfOMfQ3E2BKzmgA=",
  "URL": "https://github.com/pypa/auditwheel",
  "LICENSE": [
    "MIT"
  ],
  "ARCH": "any",
  "BUILDDATE": "1763954924",
  "PACKAGER": "eweos-x8664-worker1 <abuild@eweos-x8664-worker1>",
  "DEPENDS": [
    "python",
    "patchelf",
    "python-pyelftools",
    "python-packaging"
  ],
  "MAKEDEPENDS": [
    "python-build",
    "python-installer",
    "python-wheel",
    "python-setuptools",
    "python-setuptools-scm",
    "git"
  ],
  "REPO": "main"
}
