{ "Repository": "main", "Name": "python-pytest-enabler", "Version": "3.3.0-1", "Description": "Enable installed pytest plugins", "Architecture": "any", "URL": "https://github.com/jaraco/pytest-enabler", "Licenses": "MIT", "Groups": "None", "Provides": "None", "Depends On": "python-jaraco.context python-jaraco.functools python-pytest python-toml", "Optional Deps": "None", "Required By": "None", "Optional For": "None", "Conflicts With": "None", "Replaces": "None", "Download Size": "11.00 KiB", "Installed Size": "22.80 KiB", "Packager": "eweos-x8664-worker1 <eweos-x8664-worker1@workers.os-build.ewe.moe>", "Build Date": "Mon Oct 14 13:33:08 2024", "MD5 Sum": "f366b56613c02628d82cee4f6248aac4", "SHA-256 Sum": "6fe400168cbc48af8115620193aaf194f4bd788f95420b18edba5166002df673", "Signatures": "C358E70D77EAFF54", "Extended Data": "None" }
