{
  "FILENAME": "python-markdown-3.10.2-1-any.pkg.tar.zst",
  "NAME": "python-markdown",
  "BASE": "python-markdown",
  "VERSION": "3.10.2-1",
  "DESC": "Python implementation of John Gruber's Markdown",
  "CSIZE": "225761",
  "ISIZE": "1079557",
  "MD5SUM": "5f21572e7581156c65d3cca851fc713a",
  "SHA256SUM": "49014b141823e2a8ad876e2d858a574263a2a57c59f8ff55555d05592ae7284a",
  "PGPSIG": "iHUEABYCAB0WIQRMXo0KXwPHuyFNJ/jDWOcNd+r/VAUCabkl2wAKCRDDWOcNd+r/VMCwAP42n3Y/TUryVPNYdsvW+nvJ3rYy8WYDrUPCg6b/0YMuSgD/cdjsqwSPfnGWkri5toISF3mY2Bf1838VIBrpeWQOqwk=",
  "URL": "https://python-markdown.github.io/",
  "LICENSE": [
    "BSD-3-Clause"
  ],
  "ARCH": "any",
  "BUILDDATE": "1773741731",
  "PACKAGER": "nyaacho <abuild@nyaacho>",
  "DEPENDS": [
    "python"
  ],
  "OPTDEPENDS": [
    "python-yaml: parse Python in YAML metadata"
  ],
  "MAKEDEPENDS": [
    "git",
    "python-build",
    "python-installer",
    "python-setuptools",
    "python-wheel"
  ],
  "CHECKDEPENDS": [
    "python-yaml"
  ],
  "REPO": "main"
}
