{ "Repository": "main", "Name": "python-auditwheel", "Version": "6.1.0-1", "Description": "Auditing and relabeling cross-distribution Linux wheels.", "Architecture": "any", "URL": "https://github.com/pypa/auditwheel", "Licenses": "MIT", "Groups": "None", "Provides": "None", "Depends On": "python patchelf python-pyelftools python-packaging", "Optional Deps": "None", "Required By": "None", "Optional For": "None", "Conflicts With": "None", "Replaces": "None", "Download Size": "94.06 KiB", "Installed Size": "437.39 KiB", "Packager": "venus <venus@workers.os-build.ewe.moe>", "Build Date": "Wed Dec 4 09:32:31 2024", "MD5 Sum": "5f35786d2df091bc554e653771803cb1", "SHA-256 Sum": "eda48ef04ed482aed26ff9a5aa5ab50cd86f9321f6ba70d78c3f07bb7fe9bdd9", "Signatures": "C358E70D77EAFF54", "Extended Data": "None" }
