{ "Repository": "main", "Name": "python-numpy", "Version": "2.2.0-1", "Description": "Scientific tools for Python", "Architecture": "x86_64", "URL": "https://www.numpy.org/", "Licenses": "custom", "Groups": "None", "Provides": "None", "Depends On": "cblas lapack python", "Optional Deps": "blas-openblas: faster linear algebra", "Required By": "python-gdal python-opencv", "Optional For": "python-hypothesis", "Conflicts With": "None", "Replaces": "None", "Download Size": "9.17 MiB", "Installed Size": "44.13 MiB", "Packager": "yukari-dpc <yukari-dpc@workers.os-build.ewe.moe>", "Build Date": "Wed Dec 18 03:41:37 2024", "MD5 Sum": "76f0f4b8a32516cd8059a429294d1621", "SHA-256 Sum": "0dac63a0dd9626fb1063a2922b1fdbbf18830d68b916e283775a28d2e59fc351", "Signatures": "C358E70D77EAFF54", "Extended Data": "None" }
