{
  "FILENAME": "python-pkgconfig-1.6.0-1-any.pkg.tar.zst",
  "NAME": "python-pkgconfig",
  "BASE": "python-pkgconfig",
  "VERSION": "1.6.0-1",
  "DESC": "Python module to interface with the pkg-config command line tool",
  "CSIZE": "14705",
  "ISIZE": "42687",
  "MD5SUM": "a4d871afa7f45c41eca7159e8c959dff",
  "SHA256SUM": "6e29989591b5f113b6046d2a561fcc1c39cb2f6bf15c9db5dfe7261739794910",
  "PGPSIG": "iHUEABYCAB0WIQRMXo0KXwPHuyFNJ/jDWOcNd+r/VAUCaboNWQAKCRDDWOcNd+r/VFYZAP0QLEChV9bf3akq+n0REtY3gWQXZAKu1xr6wsEnblLUDQEApKTkmclLs1qQrwAkvaLuwvifYWapHgEk9dNN5ig0kgY=",
  "URL": "https://github.com/matze/pkgconfig",
  "LICENSE": [
    "MIT"
  ],
  "ARCH": "any",
  "BUILDDATE": "1773801001",
  "PACKAGER": "venus <abuild@venus>",
  "DEPENDS": [
    "python"
  ],
  "MAKEDEPENDS": [
    "python-build",
    "python-installer",
    "python-poetry-core"
  ],
  "CHECKDEPENDS": [
    "python-pytest",
    "python-setuptools"
  ],
  "REPO": "main"
}
