{
  "FILENAME": "qemu-system-ppc64-9.2.1-1-aarch64.pkg.tar.zst",
  "NAME": "qemu-system-ppc64",
  "BASE": "qemu",
  "VERSION": "9.2.1-1",
  "DESC": "A generic and open source machine emulator and virtualizer.",
  "CSIZE": "5108966",
  "ISIZE": "18241808",
  "MD5SUM": "b26f70640ebbaf1a85ac2a1dd1f2a2bd",
  "SHA256SUM": "65960c5528ceb1f6e27c95c293f399b9eda653136f5a44871a0c437dce70d747",
  "PGPSIG": "iF4EABYCAAYFAmetdsQACgkQw1jnDXfq/1QcIQD/Zn+P+hwsALsxlWq8QIA5wYY34jRfpK5I1+QFy5lmgJ0A/RNCfxL4pVRnTQ7fkJvhHsWAy3+9XR3VW4U1+KIMD6IF",
  "URL": "https://www.qemu.org/",
  "LICENSE": [
    "Apache-2.0",
    "BSD-2-Clause",
    "BSD-3-Clause",
    "FSFAP",
    "GPL-1.0-or-later",
    "GPL-2.0-only",
    "GPL-2.0-or-later",
    "GPL-2.0-or-later-WITH-GCC-exception-2.0",
    "LGPL-2.0-only",
    "LGPL-2.0-or-later",
    "MIT",
    "CC-BY-3.0"
  ],
  "ARCH": "aarch64",
  "BUILDDATE": "1739421129",
  "PACKAGER": "venus <venus@workers.os-build.ewe.moe>",
  "DEPENDS": [
    "pixman",
    "libpng",
    "zlib-ng",
    "libjpeg",
    "libsasl",
    "libudev",
    "libseccomp",
    "glib",
    "zstd",
    "libslirp",
    "libgcrypt",
    "libgpg-error",
    "fuse3",
    "libaio",
    "libffi",
    "pcre2",
    "libfdt",
    "qemu-common=9.2.1-1"
  ],
  "REPO": "main"
}
