{ "Repository": "main", "Name": "qt6-5compat", "Version": "6.7.2-1", "Description": "Module that contains unsupported Qt 5 APIs", "Architecture": "riscv64", "URL": "https://www.qt.io", "Licenses": "GPL3 LGPL3 FDL custom", "Groups": "qt6", "Provides": "None", "Depends On": "qt6-base qt6-shadertools icu", "Optional Deps": "qt6-declarative: for QtGraphicalEffects", "Required By": "kdegraphics-mobipocket kio konversation libplasma qca-qt6", "Optional For": "mlt", "Conflicts With": "None", "Replaces": "None", "Download Size": "480.23 KiB", "Installed Size": "1444.95 KiB", "Packager": "eweos-riscv64-lpi4aworker2 <eweos-riscv64-lpi4aworker2@workers.os-build.ewe.moe>", "Build Date": "Thu Oct 17 06:28:16 2024", "MD5 Sum": "1d02c62f7d82a21f01e3e89e92bde078", "SHA-256 Sum": "a56c9ea7693ccd83a0a68cf655fd606947360fbaaccb09e8bc339df53af329c2", "Signatures": "C358E70D77EAFF54", "Extended Data": "None" }
