{
  "FILENAME": "rust-src-1.84.1-1-riscv64.pkg.tar.zst",
  "NAME": "rust-src",
  "BASE": "rust",
  "VERSION": "1.84.1-1",
  "DESC": "Source code for the Rust standard library",
  "CSIZE": "4580375",
  "ISIZE": "33400535",
  "MD5SUM": "2392822df9bc9c820e0a78a5f4c73904",
  "SHA256SUM": "9d91625172f6687ed7bc7b3923f68db8fdc7c9af209f9adfdb9e92262d3f08c5",
  "PGPSIG": "iF4EABYCAAYFAmetl/YACgkQw1jnDXfq/1RtswEA60ZZDPad9/SiA7kZEGyZAHautwcFXC0yV5wOOx4yiPkA/R9F840cDTbselv49X7u8w4qVuxb1K2BxrgYpXw84zMI",
  "URL": "https://www.rust-lang.org/",
  "LICENSE": [
    "MIT",
    "Apache"
  ],
  "ARCH": "riscv64",
  "BUILDDATE": "1739415779",
  "PACKAGER": "visionfive2-2 <visionfive2-2@workers.os-build.ewe.moe>",
  "DEPENDS": [
    "rust"
  ],
  "REPO": "main"
}
