{
  "FILENAME": "solid-6.15.0-1-loongarch64.pkg.tar.zst",
  "NAME": "solid",
  "BASE": "solid",
  "VERSION": "6.15.0-1",
  "DESC": "Hardware integration and detection",
  "GROUPS": "kf6",
  "CSIZE": "409805",
  "ISIZE": "1932295",
  "MD5SUM": "c4b366ccc58f4f8975ccf950fbe186d6",
  "SHA256SUM": "f911433d55ee01dfea618ec4bc2471fe832106875b1e136de7ed95604a113fe8",
  "PGPSIG": "iF4EABYCAAYFAmhb3OoACgkQw1jnDXfq/1RNhgD/dRkDPLjDeYjHMN9quLgrYXSKePDra/wwtB3ppVWz4igA/18AxvSW/qY1TBFx4/oOQLxEnbUazve9/jb1P6cVXVEM",
  "URL": "https://community.kde.org/Frameworks",
  "LICENSE": [
    "LGPL-2.0-only",
    "LGPL-3.0-only"
  ],
  "ARCH": "loongarch64",
  "BUILDDATE": "1750851120",
  "PACKAGER": "eweos-loong64-3a6000worker1 <eweos-loong64-3a6000worker1@workers.os-build.ewe.moe>",
  "DEPENDS": [
    "qt6-base",
    "util-linux-libs"
  ],
  "OPTDEPENDS": [
    "qt5-declarative: QML bindings"
  ],
  "MAKEDEPENDS": [
    "extra-cmake-modules",
    "linux-headers",
    "qt6-declarative",
    "qt6-tools"
  ],
  "REPO": "main"
}
