{
  "FILENAME": "strace-6.13-1-x86_64.pkg.tar.zst",
  "NAME": "strace",
  "BASE": "strace",
  "VERSION": "6.13-1",
  "DESC": "A diagnostic, debugging and instructional userspace tracer",
  "CSIZE": "611911",
  "ISIZE": "1840790",
  "MD5SUM": "9857ffd1be350fad0d151f387a626633",
  "SHA256SUM": "1868a060973af9aab6846b1d5355f774b9fb556b2b3a91f2e98b5174deb3d1ec",
  "PGPSIG": "iF4EABYCAAYFAmegl5gACgkQw1jnDXfq/1QWZgD/btpgf5duU6hDVDhrWVkwmmMBrIfFYbhFh9DQ9QUg2QIBANY3dxpxLGivOLuhXRgCmsBv05FSl1MIh0n3hN3b2/MN",
  "URL": "https://strace.io/",
  "LICENSE": [
    "BSD"
  ],
  "ARCH": "x86_64",
  "BUILDDATE": "1738578199",
  "PACKAGER": "eweos-x8664-worker1 <eweos-x8664-worker1@workers.os-build.ewe.moe>",
  "DEPENDS": [
    "perl"
  ],
  "REPO": "main"
}
