{
  "FILENAME": "ttf-noto-sans-mono-2025.05.01-3-any.pkg.tar.zst",
  "NAME": "ttf-noto-sans-mono",
  "BASE": "font-noto",
  "VERSION": "2025.05.01-3",
  "DESC": "Google Noto TTF fonts (Sans Mono)",
  "CSIZE": "7729260",
  "ISIZE": "21495249",
  "MD5SUM": "06c435c5b761ee9fd107cc421813072e",
  "SHA256SUM": "5f868c088fa2f055b937abd19a9f1915bfab1798a492750b6df4bd2e152fcd82",
  "PGPSIG": "iF4EABYCAAYFAmikQL0ACgkQw1jnDXfq/1R+ogD+IQfDLREQ9cKA6A4eMvGEuScuUUltmnY6S+LXWQ22Ly4BAIrV3r3kruJ5p4v/46eB7aLu/IRsSQlBJN2vwateWfgD",
  "URL": "https://fonts.google.com/noto",
  "LICENSE": [
    "custom:SIL"
  ],
  "ARCH": "any",
  "BUILDDATE": "1755595609",
  "PACKAGER": "nyaacho <nyaacho@workers.os-build.ewe.moe>",
  "PROVIDES": [
    "font-noto-sans-mono"
  ],
  "MAKEDEPENDS": [
    "git"
  ],
  "REPO": "main"
}
