{ "Repository": "main", "Name": "ttf-zed-mono-nerd", "Version": "3.3.0-1", "Description": "Patched font Zed Mono from nerd fonts library", "Architecture": "any", "URL": "https://github.com/ryanoasis/nerd-fonts", "Licenses": "OFL-1.1-no-RFN", "Groups": "nerd-fonts", "Provides": "ttf-font-nerd", "Depends On": "None", "Optional Deps": "None", "Required By": "None", "Optional For": "None", "Conflicts With": "None", "Replaces": "None", "Download Size": "226.54 MiB", "Installed Size": "696.70 MiB", "Packager": "eweos-loong64-3a6000worker1 <eweos-loong64-3a6000worker1@workers.os-build.ewe.moe>", "Build Date": "Wed Nov 20 07:18:51 2024", "MD5 Sum": "8d8571bdce13601569741a49167fd440", "SHA-256 Sum": "cbc817c74c3337a0c68c5ae52fc7d077ed473d079213b2f5de10287aa2321147", "Signatures": "C358E70D77EAFF54", "Extended Data": "None" }
