{
  "FILENAME": "ttf-monofur-nerd-3.3.0-1-any.pkg.tar.zst",
  "NAME": "ttf-monofur-nerd",
  "BASE": "font-nerd",
  "VERSION": "3.3.0-1",
  "DESC": "Patched font Monofur from nerd fonts library",
  "GROUPS": "nerd-fonts",
  "CSIZE": "12741152",
  "ISIZE": "22192764",
  "MD5SUM": "00ad3dfd1caa72c86782b699e9e43fec",
  "SHA256SUM": "7e14d2d0f5b2dd3160505c8a7a814a7863f42cb08aadf8aacbf011b5ad0ee583",
  "PGPSIG": "iF4EABYCAAYFAmc9jZwACgkQw1jnDXfq/1QfhwD+OONnwxbXmw27mJcllgi0O7uUO8u7HVMHZeXnYG3pfoEBAPWZMBCwXL20gU2ybsjf3BLrhf9me7DTzfLyqbQcY1gK",
  "URL": "https://github.com/ryanoasis/nerd-fonts",
  "LICENSE": [
    "LicenseRef-Monofur-Free-License"
  ],
  "ARCH": "any",
  "BUILDDATE": "1732087098",
  "PACKAGER": "eweos-x8664-worker1 <eweos-x8664-worker1@workers.os-build.ewe.moe>",
  "REPLACES": [
    "nerd-fonts-monofur"
  ],
  "CONFLICTS": [
    "nerd-fonts-monofur"
  ],
  "PROVIDES": [
    "ttf-font-nerd"
  ],
  "REPO": "main"
}
