{ "Repository": "main", "Name": "ttf-bigblueterminal-nerd", "Version": "3.3.0-1", "Description": "Patched font Big Blue Terminal from nerd fonts library", "Architecture": "any", "URL": "https://github.com/ryanoasis/nerd-fonts", "Licenses": "CC-BY-SA-4.0", "Groups": "nerd-fonts", "Provides": "ttf-font-nerd", "Depends On": "None", "Optional Deps": "None", "Required By": "None", "Optional For": "None", "Conflicts With": "None", "Replaces": "None", "Download Size": "7.27 MiB", "Installed Size": "12.84 MiB", "Packager": "visionfive2-1 <visionfive2-1@workers.os-build.ewe.moe>", "Build Date": "Wed Nov 20 08:42:53 2024", "MD5 Sum": "5c2773203e403a86362ec7b42e3855c5", "SHA-256 Sum": "218a6eb3250414a4b0a3d4f0d5eeda0652a6df01bb7f499f4e4f2fb578bab1a5", "Signatures": "C358E70D77EAFF54", "Extended Data": "None" }
