{
  "FILENAME": "ttf-cascadia-mono-nerd-3.4.0-1-any.pkg.tar.zst",
  "NAME": "ttf-cascadia-mono-nerd",
  "BASE": "font-nerd",
  "VERSION": "3.4.0-1",
  "DESC": "Patched font Cascadia Mono (Caskaydia) from nerd fonts library",
  "GROUPS": [
    "nerd-fonts"
  ],
  "CSIZE": "54059442",
  "ISIZE": "100472627",
  "MD5SUM": "b486e39b2859e37cb8cae582f8213717",
  "SHA256SUM": "286c931c6b72ac163fd4c347f2819add7583099fe1988838225b9235997abb65",
  "PGPSIG": "iF4EABYCAAYFAmhVNaIACgkQw1jnDXfq/1To3wD+OntgTsV85+CQa88uzbgH2UcWGOrcxImEzdkHasHyjmMA/3vs3hPY7yK48lJcaf2NWhQFdqRX7XAB2KLNkMx4C8kF",
  "URL": "https://github.com/ryanoasis/nerd-fonts",
  "LICENSE": [
    "OFL-1.1-RFN"
  ],
  "ARCH": "any",
  "BUILDDATE": "1750413516",
  "PACKAGER": "visionfive2-2 <visionfive2-2@workers.os-build.ewe.moe>",
  "PROVIDES": [
    "ttf-font-nerd"
  ],
  "REPO": "main"
}
