{
  "FILENAME": "vulkan-mesa-layers-24.3.4-1-x86_64.pkg.tar.zst",
  "NAME": "vulkan-mesa-layers",
  "BASE": "mesa",
  "VERSION": "24.3.4-1",
  "DESC": "Mesa's Vulkan layers",
  "CSIZE": "428882",
  "ISIZE": "1196682",
  "MD5SUM": "b75d6dbf4fe12070646387d8ca3a44ad",
  "SHA256SUM": "43e7cfffbbf3515f5ea66132d412d7cebea85d7fe42c2286eeb73d23e4214184",
  "PGPSIG": "iF4EABYCAAYFAmemAxMACgkQw1jnDXfq/1RFLwEAokWYWoMsCJHdZ34GBb8CfYZUd7lxNcC1whh6yDTyxNIBAOoFNR/+n/dJWVW6jqduZJ7fcPCN6LJA6cMrWnqOW1YD",
  "URL": "https://www.mesa3d.org/",
  "LICENSE": [
    "custom"
  ],
  "ARCH": "x86_64",
  "BUILDDATE": "1738933306",
  "PACKAGER": "eweos-x8664-worker1 <eweos-x8664-worker1@workers.os-build.ewe.moe>",
  "DEPENDS": [
    "libdrm",
    "wayland",
    "python"
  ],
  "REPO": "main"
}
