{ "Repository": "main", "Name": "wlroots0.17", "Version": "0.17.4-5", "Description": "Modular Wayland compositor library", "Architecture": "riscv64", "URL": "https://gitlab.freedesktop.org/wlroots/wlroots", "Licenses": "MIT", "Groups": "None", "Provides": "libwlroots.so.12", "Depends On": "libdrm libinput seatd libudev-zero libxkbcommon libgles libegl pixman wayland libdisplay-info", "Optional Deps": "None", "Required By": "wayfire wcm wlroots0.17-devel", "Optional For": "None", "Conflicts With": "None", "Replaces": "None", "Download Size": "325.61 KiB", "Installed Size": "750.06 KiB", "Packager": "visionfive2-1 <visionfive2-1@workers.os-build.ewe.moe>", "Build Date": "Sat Oct 19 15:44:16 2024", "MD5 Sum": "e679a0601fab4ac6feaec8e60b824496", "SHA-256 Sum": "29d1d49340ea921c6b0c847de5b35dcb51a986e53aca4093c8445aac4e5c8065", "Signatures": "C358E70D77EAFF54", "Extended Data": "None" }
