{ "Repository": "main", "Name": "xfce4-places-plugin", "Version": "1.8.3-1", "Description": "A menu with quick access to folders, documents, and removable media", "Architecture": "riscv64", "URL": "https://docs.xfce.org/panel-plugins/xfce4-places-plugin/start", "Licenses": "GPL-2.0-or-later", "Groups": "xfce4-goodies", "Provides": "None", "Depends On": "libnotify xfce4-panel", "Optional Deps": "None", "Required By": "None", "Optional For": "None", "Conflicts With": "None", "Replaces": "None", "Download Size": "73.17 KiB", "Installed Size": "236.07 KiB", "Packager": "eweos-riscv64-lpi4aworker2 <eweos-riscv64-lpi4aworker2@workers.os-build.ewe.moe>", "Build Date": "Thu Dec 5 04:22:51 2024", "MD5 Sum": "1b592abd08b102525362a54f7476a34d", "SHA-256 Sum": "573070ec497fc178c6a86488f5474a666931f5b573dea598a4584bf9c9dea72c", "Signatures": "C358E70D77EAFF54", "Extended Data": "None" }
