{ "Repository": "main", "Name": "xfce4-whiskermenu-plugin", "Version": "2.8.3-1", "Description": "Menu for Xfce4", "Architecture": "x86_64", "URL": "https://docs.xfce.org/panel-plugins/xfce4-whiskermenu-plugin/start", "Licenses": "GPL-2.0-or-later", "Groups": "xfce4-goodies", "Provides": "None", "Depends On": "garcon gtk3 gtk-layer-shell xfce4-panel", "Optional Deps": "None", "Required By": "None", "Optional For": "None", "Conflicts With": "None", "Replaces": "None", "Download Size": "242.81 KiB", "Installed Size": "688.58 KiB", "Packager": "eweos-x8664-worker1 <eweos-x8664-worker1@workers.os-build.ewe.moe>", "Build Date": "Thu Dec 5 04:15:38 2024", "MD5 Sum": "59931ff2d1c6414c4340a105d54645cc", "SHA-256 Sum": "2a1414fe636fd1d1e1975bffc7f13cfd81722458117baec0da70e0d01c323e61", "Signatures": "C358E70D77EAFF54", "Extended Data": "None" }
