{ "Repository": "main", "Name": "zita-convolver", "Version": "4.0.3-1", "Description": "A fast, partitioned convolution engine library.", "Architecture": "riscv64", "URL": "https://kokkinizita.linuxaudio.org/linuxaudio/", "Licenses": "GPL3", "Groups": "None", "Provides": "libzita-convolver.so", "Depends On": "fftw", "Optional Deps": "None", "Required By": "None", "Optional For": "None", "Conflicts With": "None", "Replaces": "None", "Download Size": "17.42 KiB", "Installed Size": "34.75 KiB", "Packager": "eweos-riscv64-lpi4aworker2 <eweos-riscv64-lpi4aworker2@workers.os-build.ewe.moe>", "Build Date": "Thu Dec 5 06:29:35 2024", "MD5 Sum": "42b62f611c853008b57c19decef34518", "SHA-256 Sum": "130aad8baaf26267c2fbff9e5cca0f8c1381ca474a7dac6218925d2b48699be0", "Signatures": "C358E70D77EAFF54", "Extended Data": "None" }
